pyctcdecode/__init__.py
pyctcdecode/alphabet.py
pyctcdecode/constants.py
pyctcdecode/decoder.py
pyctcdecode/language_model.py
pyctcdecode/py.typed
pyctcdecode/tests/sample_data/bugs_bunny_kenlm.arpa
pyctcdecode/tests/sample_data/libri_logits.json
pyctcdecode-0.5.0.dist-info/AUTHORS.md
pyctcdecode-0.5.0.dist-info/LICENSE
pyctcdecode-0.5.0.dist-info/METADATA
pyctcdecode-0.5.0.dist-info/WHEEL
pyctcdecode-0.5.0.dist-info/top_level.txt
pyctcdecode-0.5.0.dist-info/RECORD
