Metadata-Version: 2.1
Name: pyctcdecode
Version: 0.5.0
Summary: CTC beam search decoder for speech recognition.
Author-email: "Kensho Technologies, LLC." <pyctcdecode-maintainer@kensho.com>
License: 
Project-URL: source, https://github.com/kensho-technologies/pyctcdecode
Requires-Python: >=3.7
License-File: LICENSE
License-File: AUTHORS.md
Requires-Dist: numpy (<2.0.0,>=1.15.0)
Requires-Dist: pygtrie (<3.0,>=2.1)
Requires-Dist: hypothesis (<7,>=6.14)
Requires-Dist: importlib-metadata (<5) ; python_version == "3.7"
Provides-Extra: dev
Requires-Dist: bandit ; extra == 'dev'
Requires-Dist: black ; extra == 'dev'
Requires-Dist: codecov ; extra == 'dev'
Requires-Dist: flake8 ; extra == 'dev'
Requires-Dist: huggingface-hub ; extra == 'dev'
Requires-Dist: isort (<6,>=5.0.0) ; extra == 'dev'
Requires-Dist: jupyter ; extra == 'dev'
Requires-Dist: mypy ; extra == 'dev'
Requires-Dist: nbconvert ; extra == 'dev'
Requires-Dist: nbformat ; extra == 'dev'
Requires-Dist: pydocstyle ; extra == 'dev'
Requires-Dist: pylint ; extra == 'dev'
Requires-Dist: pytest ; extra == 'dev'
Requires-Dist: pytest-cov ; extra == 'dev'
